enhanced_http/__init__.py
enhanced_http/cache.py
enhanced_http/client.py
enhanced_http/middleware.py
enhanced_http/utils.py
enhanced_http/websocket.py
enhanced_http/tests/__init__.py
enhanced_http/tests/test_cache.py
enhanced_http/tests/test_client.py
enhanced_http/tests/test_websocket.py
enhanced_http-1.0.0.dist-info/LICENSE
enhanced_http-1.0.0.dist-info/METADATA
enhanced_http-1.0.0.dist-info/WHEEL
enhanced_http-1.0.0.dist-info/top_level.txt
enhanced_http-1.0.0.dist-info/RECORD
