Metadata-Version: 2.1
Name: enhanced-http
Version: 1.0.0
Summary: A lightweight, production-ready asynchronous HTTP client.
Home-page: https://github.com/Treytek/enhanced_http
Author: Dean Goss
Author-email: dgoss@treytek.com
License: MIT
Project-URL: Source, https://github.com/Treytek/enhanced-http
Project-URL: Tracker, https://github.com/Treytek/enhanced-http/issues
Keywords: http client,websocket,asyncio,middleware,caching
Classifier: Programming Language :: Python :: 3
Classifier: License :: OSI Approved :: MIT License
Classifier: Operating System :: OS Independent
Classifier: Topic :: Software Development :: Libraries
Classifier: Topic :: Internet :: WWW/HTTP
Requires-Python: >=3.7
License-File: LICENSE
Provides-Extra: dev
Requires-Dist: pytest; extra == "dev"
Requires-Dist: pytest-asyncio; extra == "dev"
Requires-Dist: pytest-xdist; extra == "dev"
